notolog/__init__.py
notolog/app.py
notolog/app_config.py
notolog/app_package.py
notolog/assets/fonts/IBMPlexMono/IBMPlexMono-Regular.ttf
notolog/assets/fonts/IBMPlexMono/OFL.txt
notolog/assets/fonts/NotoSans/NotoSans-Regular.ttf
notolog/assets/fonts/NotoSans/OFL.txt
notolog/assets/notolog-example-image.png
notolog/assets/notolog-logo.png
notolog/assets/themes/calligraphy/about_popup.css
notolog/assets/themes/calligraphy/ai_assistant.css
notolog/assets/themes/calligraphy/default.ini
notolog/assets/themes/calligraphy/editor.css
notolog/assets/themes/calligraphy/md.ini
notolog/assets/themes/calligraphy/settings_dialog.css
notolog/assets/themes/calligraphy/statusbar.css
notolog/assets/themes/calligraphy/styles.css
notolog/assets/themes/calligraphy/toolbar.css
notolog/assets/themes/calligraphy/tree_view.css
notolog/assets/themes/calligraphy/viewer.css
notolog/assets/themes/calligraphy/viewer.ini
notolog/assets/themes/default/about_popup.css
notolog/assets/themes/default/ai_assistant.css
notolog/assets/themes/default/default.ini
notolog/assets/themes/default/editor.css
notolog/assets/themes/default/icons/LICENSE
notolog/assets/themes/default/icons/arrow-clockwise.svg
notolog/assets/themes/default/icons/arrow-left.svg
notolog/assets/themes/default/icons/arrow-repeat.svg
notolog/assets/themes/default/icons/arrow-right.svg
notolog/assets/themes/default/icons/balloon-fill.svg
notolog/assets/themes/default/icons/balloon.svg
notolog/assets/themes/default/icons/bandaid-fill.svg
notolog/assets/themes/default/icons/bandaid.svg
notolog/assets/themes/default/icons/box-arrow-up-right.svg
notolog/assets/themes/default/icons/box-arrow-up.svg
notolog/assets/themes/default/icons/caret-down-fill.svg
notolog/assets/themes/default/icons/caret-up-fill.svg
notolog/assets/themes/default/icons/clock-fill.svg
notolog/assets/themes/default/icons/code-slash.svg
notolog/assets/themes/default/icons/copy.svg
notolog/assets/themes/default/icons/cpu.svg
notolog-1.1.9.dist-info/METADATA
notolog-1.1.9.dist-info/WHEEL
notolog-1.1.9.dist-info/entry_points.txt
notolog-1.1.9.dist-info/licenses/LICENSE
notolog-1.1.9.dist-info/RECORD
