Metadata-Version: 2.4
Name: notolog
Version: 1.1.9
Summary: Notolog - Python Markdown Editor
License: MIT
License-File: LICENSE
Keywords: notolog,python,markdown,editor,ai,llm,text,notes,pyside6,qt,gguf,onnx,llama-cpp,local-llm,privacy,encryption,note-taking,syntax-highlighting,ai-assistant,on-device-llm,offline-ai,phi-4,mistral,qwen,writing-assistant,markdown-editor,cross-platform,open-source
Author: Vadim Bakhrenkov
Requires-Python: >=3.10,<3.15
Classifier: Development Status :: 5 - Production/Stable
Classifier: Intended Audience :: Developers
Classifier: Intended Audience :: End Users/Desktop
Classifier: License :: OSI Approved :: MIT License
Classifier: Natural Language :: Chinese (Simplified)
Classifier: Natural Language :: Dutch
Classifier: Natural Language :: English
Classifier: Natural Language :: Finnish
Classifier: Natural Language :: French
Classifier: Natural Language :: Georgian
Classifier: Natural Language :: German
Classifier: Natural Language :: Greek
Classifier: Natural Language :: Hindi
Classifier: Natural Language :: Indonesian
Classifier: Natural Language :: Italian
Classifier: Natural Language :: Japanese
Classifier: Natural Language :: Korean
Classifier: Natural Language :: Latin
Classifier: Natural Language :: Portuguese
Classifier: Natural Language :: Russian
Classifier: Natural Language :: Spanish
Classifier: Natural Language :: Swedish
Classifier: Natural Language :: Turkish
Classifier: Operating System :: MacOS
Classifier: Operating System :: Microsoft :: Windows
Classifier: Operating System :: OS Independent
Classifier: Operating System :: POSIX
Classifier: Operating System :: Unix
Classifier: Programming Language :: Python :: 3
Classifier: Programming Language :: Python :: 3.10
Classifier: Programming Language :: Python :: 3.11
Classifier: Programming Language :: Python :: 3.12
Classifier: Programming Language :: Python :: 3.13
Classifier: Programming Language :: Python :: 3.14
Classifier: Programming Language :: Python :: 3 :: Only
Classifier: Topic :: Text Editors
Classifier: Topic :: Text Editors :: Documentation
Classifier: Topic :: Text Editors :: Emacs
Classifier: Topic :: Text Editors :: Integrated Development Environments (IDE)
Classifier: Topic :: Text Editors :: Text Processing
Classifier: Topic :: Text Editors :: Word Processors
Classifier: Topic :: Text Processing
Classifier: Topic :: Text Processing :: General
Classifier: Topic :: Text Processing :: Markup :: Markdown
Provides-Extra: llama
Requires-Dist: Markdown (>=3.7,<4.0)
Requires-Dist: PySide6_Essentials (>=6.8.0.2)
Requires-Dist: Pygments (>=2.18.0,<3.0.0)
Requires-Dist: cffi (>=1.17.0)
Requires-Dist: click (>=8.1.7,<9.0.0)
Requires-Dist: cryptography (>=43.0.1)
Requires-Dist: emoji (>=2.14.0,<3.0.0)
Requires-Dist: iniconfig (>=2.0.0,<3.0.0)
Requires-Dist: llama-cpp-python (>=0.3.8,<0.4.0) ; extra == "llama"
Requires-Dist: numpy (>=2.1.0,<3.0.0)
Requires-Dist: onnxruntime-genai (>=0.11.0,<1.0.0) ; python_version >= "3.10" and python_version < "3.14"
Requires-Dist: packaging (>=24.0)
Requires-Dist: pluggy (>=1.5.0,<2.0.0)
Requires-Dist: pycparser (>=3.0,<4.0)
Requires-Dist: qasync (>=0.27.1)
Requires-Dist: shiboken6 (>=6.8.0.2)
Requires-Dist: tomli (>=2.0.1,<3.0.0)
Requires-Dist: tomli_w (>=1.0.0,<2.0.0)
Requires-Dist: typing_extensions (>=4.12.0,<5.0.0)
Project-URL: Changelog, https://github.com/notolog/notolog-editor/blob/main/CHANGELOG.md
Project-URL: Documentation, https://notolog.app
Project-URL: Homepage, https://notolog.app
Project-URL: IssueTracker, https://github.com/notolog/notolog-editor/issues
Project-URL: Repository, https://github.com/notolog/notolog-editor
